{
    "W": [{
        "onPress": {
            "class": "local.autohotkey.data.macro.Memorize",
            "params": [
                "W"
            ]
        }
    }],
    "A": [{
        "onPress": {
            "class": "local.autohotkey.data.macro.Memorize",
            "params": [
                "A"
            ]
        }
    }],
    "S": [{
        "onPress": {
            "class": "local.autohotkey.data.macro.Memorize",
            "params": [
                "S"
            ]
        }
    }],
    "D": [{
        "onPress": {
            "class": "local.autohotkey.data.macro.Memorize",
            "params": [
                "D"
            ]
        }
    }],
    "LSHIFT": [{
        "onPress": {
            "class": "local.autohotkey.data.macro.cyberpunk.Avoid",
            "params": [
            ]
        }
    }],
    "PGUP": [{
        "onPress": {
            "class": "local.autohotkey.data.macro.GestureMacro",
            "params": [
                "F13",
                "F14",
                "F15",
                "F16"
            ]
        }
    }],
    "PGDN": [{
        "onPress": {
            "class": "local.autohotkey.data.macro.GestureMacro",
            "params": [
                "F17",
                "F18",
                "F19",
                "F20"
            ]
        }
    }],
    "MEDIA_STOP": [
        {
            "onPress": {
                "class": "local.autohotkey.data.macro.StopApplication",
                "params": [
                ]
            }
        }
    ]
}